pintools/__init__.py
pintools/__main__.py
pintools/pin_tags.py
pintools/pinhub.py
pintools/pintools.py
pintools/reddit_to_pinboard.py
pintools/title_fix.py
pintools/utils.py
pintools-1.0.3.dist-info/LICENSE
pintools-1.0.3.dist-info/METADATA
pintools-1.0.3.dist-info/WHEEL
pintools-1.0.3.dist-info/entry_points.txt
pintools-1.0.3.dist-info/top_level.txt
pintools-1.0.3.dist-info/RECORD
