Metadata-Version: 2.1
Name: pintools
Version: 1.0.3
Summary: Tools importing links from various services to Pinboard
Home-page: https://github.com/patrickleweryharris/pintools
Author: Patrick Harris
Author-email: patrick@plh.io
License: UNKNOWN
Platform: UNKNOWN
Classifier: Programming Language :: Python :: 3
Classifier: License :: OSI Approved :: MIT License
Classifier: Operating System :: Unix
Requires-Python: >=3.5
Requires-Dist: pinboard
Requires-Dist: praw
Requires-Dist: PyGithub
